{
  "info": {
    "_postman_id": "8eb5b031-bee5-4747-a219-415e01c26b6e",
    "name": "Task Management API",
    "schema": "https://schema.getpostman.com/json/collection/v2.1.0/collection.json",
    "_exporter_id": "51802314",
    "_collection_link": "https://go.postman.co/collection/51802314-8eb5b031-bee5-4747-a219-415e01c26b6e?source=collection_link"
  },
  "item": [
    {
      "name": "Teams",
      "item": [
        {
          "name": "Create Team",
          "request": {
            "auth": {
              "type": "bearer",
              "bearer": [
                {
                  "key": "token",
                  "value": "{{managerToken}}",
                  "type": "string"
                }
              ]
            },
            "method": "POST",
            "header": [],
            "body": {
              "mode": "raw",
              "raw": "{\r\n  \"name\": \"Backend Team\"\r\n}",
              "options": {
                "raw": {
                  "language": "json"
                }
              }
            },
            "url": {
              "raw": "{{baseUrl}}/api/teams",
              "host": [
                "{{baseUrl}}"
              ],
              "path": [
                "api",
                "teams"
              ]
            }
          },
          "response": []
        },
        {
          "name": "Get Teams",
          "request": {
            "auth": {
              "type": "bearer",
              "bearer": [
                {
                  "key": "token",
                  "value": "{{managerToken}}",
                  "type": "string"
                }
              ]
            },
            "method": "GET",
            "header": [],
            "url": {
              "raw": "{{baseUrl}}/api/teams",
              "host": [
                "{{baseUrl}}"
              ],
              "path": [
                "api",
                "teams"
              ]
            }
          },
          "response": []
        },
        {
          "name": "Update Team",
          "request": {
            "auth": {
              "type": "bearer",
              "bearer": [
                {
                  "key": "token",
                  "value": "{{managerToken}}",
                  "type": "string"
                }
              ]
            },
            "method": "PUT",
            "header": [],
            "body": {
              "mode": "raw",
              "raw": "{\r\n  \"name\": \"Updated New Backend Team\"\r\n}",
              "options": {
                "raw": {
                  "language": "json"
                }
              }
            },
            "url": {
              "raw": "{{baseUrl}}/api/teams/{{teamId}}",
              "host": [
                "{{baseUrl}}"
              ],
              "path": [
                "api",
                "teams",
                "{{teamId}}"
              ]
            }
          },
          "response": []
        },
        {
          "name": "Delete Team",
          "request": {
            "auth": {
              "type": "bearer",
              "bearer": [
                {
                  "key": "token",
                  "value": "{{managerToken}}",
                  "type": "string"
                }
              ]
            },
            "method": "DELETE",
            "header": [],
            "url": {
              "raw": "{{baseUrl}}/api/teams/{{teamId}}",
              "host": [
                "{{baseUrl}}"
              ],
              "path": [
                "api",
                "teams",
                "{{teamId}}"
              ]
            }
          },
          "response": []
        },
        {
          "name": "Forbidden Team Create",
          "request": {
            "auth": {
              "type": "bearer",
              "bearer": [
                {
                  "key": "token",
                  "value": "{{memberToken}}",
                  "type": "string"
                }
              ]
            },
            "method": "POST",
            "header": [],
            "body": {
              "mode": "raw",
              "raw": "{\r\n  \"name\": \"Unauthorized Team\"\r\n}",
              "options": {
                "raw": {
                  "language": "json"
                }
              }
            },
            "url": {
              "raw": "{{baseUrl}}/api/teams",
              "host": [
                "{{baseUrl}}"
              ],
              "path": [
                "api",
                "teams"
              ]
            }
          },
          "response": []
        },
        {
          "name": "Unauthorized Teams Access",
          "request": {
            "method": "GET",
            "header": [],
            "url": {
              "raw": "{{baseUrl}}/api/teams",
              "host": [
                "{{baseUrl}}"
              ],
              "path": [
                "api",
                "teams"
              ]
            }
          },
          "response": []
        }
      ]
    },
    {
      "name": "Auth",
      "item": [
        {
          "name": "Register Manager",
          "request": {
            "method": "POST",
            "header": [],
            "body": {
              "mode": "raw",
              "raw": "{\r\n  \"name\": \"Manager User\",\r\n  \"email\": \"manager2@test.com\",\r\n  \"password\": \"123456\",\r\n  \"role\": \"manager\"\r\n}",
              "options": {
                "raw": {
                  "language": "json"
                }
              }
            },
            "url": {
              "raw": "{{baseUrl}}/api/auth/register",
              "host": [
                "{{baseUrl}}"
              ],
              "path": [
                "api",
                "auth",
                "register"
              ]
            }
          },
          "response": []
        },
        {
          "name": "REGISTER MEMBER",
          "request": {
            "method": "POST",
            "header": [],
            "body": {
              "mode": "raw",
              "raw": "{\r\n  \"name\": \"Member User\",\r\n  \"email\": \"member2@test.com\",\r\n  \"password\": \"123456\",\r\n  \"role\": \"member\"\r\n}",
              "options": {
                "raw": {
                  "language": "json"
                }
              }
            },
            "url": {
              "raw": "{{baseUrl}}/api/auth/register",
              "host": [
                "{{baseUrl}}"
              ],
              "path": [
                "api",
                "auth",
                "register"
              ]
            }
          },
          "response": []
        },
        {
          "name": "Login Manager",
          "request": {
            "method": "POST",
            "header": [],
            "body": {
              "mode": "raw",
              "raw": "{\r\n  \"email\": \"manager2@test.com\",\r\n  \"password\": \"123456\"\r\n}",
              "options": {
                "raw": {
                  "language": "json"
                }
              }
            },
            "url": {
              "raw": "{{baseUrl}}/api/auth/login",
              "host": [
                "{{baseUrl}}"
              ],
              "path": [
                "api",
                "auth",
                "login"
              ]
            }
          },
          "response": []
        },
        {
          "name": "Login Member",
          "request": {
            "method": "POST",
            "header": [],
            "body": {
              "mode": "raw",
              "raw": "{\r\n  \"email\": \"member2@test.com\",\r\n  \"password\": \"123456\"\r\n}",
              "options": {
                "raw": {
                  "language": "json"
                }
              }
            },
            "url": {
              "raw": "{{baseUrl}}/api/auth/login",
              "host": [
                "{{baseUrl}}"
              ],
              "path": [
                "api",
                "auth",
                "login"
              ]
            }
          },
          "response": []
        },
        {
          "name": "Get Me",
          "request": {
            "auth": {
              "type": "bearer",
              "bearer": [
                {
                  "key": "token",
                  "value": "{{managerToken}}",
                  "type": "string"
                }
              ]
            },
            "method": "GET",
            "header": [],
            "url": {
              "raw": "{{baseUrl}}/api/auth/me",
              "host": [
                "{{baseUrl}}"
              ],
              "path": [
                "api",
                "auth",
                "me"
              ]
            }
          },
          "response": []
        }
      ]
    },
    {
      "name": "Health",
      "item": [
        {
          "name": "HEALTH CHECK",
          "request": {
            "method": "GET",
            "header": [],
            "url": {
              "raw": "{{baseUrl}}/api/health",
              "host": [
                "{{baseUrl}}"
              ],
              "path": [
                "api",
                "health"
              ]
            }
          },
          "response": []
        }
      ]
    }
  ]
}